Metadata-Version: 2.1
Name: plshandle
Version: 0.2
Summary: UNKNOWN
Home-page: https://github.com/v7a/plshandle
Author: v7a
License: UNKNOWN
Project-URL: Documentation, https://plshandle.readthedocs.io
Project-URL: Source, https://github.com/v7a/plshandle
Project-URL: Tracker, https://github.com/v7a/plshandle/issues
Keywords: exception,contract,error handling
Platform: UNKNOWN
Classifier: Development Status :: 4 - Beta
Classifier: Intended Audience :: Developers
Classifier: Programming Language :: Python :: 3 :: Only
Classifier: License :: OSI Approved :: MIT License
Classifier: Operating System :: OS Independent
Classifier: Topic :: Software Development :: Quality Assurance
Classifier: Topic :: Software Development :: Testing
